procclean/__init__.py
procclean/__main__.py
procclean/cli/__init__.py
procclean/cli/commands.py
procclean/cli/docs.py
procclean/cli/parser.py
procclean/core/__init__.py
procclean/core/actions.py
procclean/core/constants.py
procclean/core/filters.py
procclean/core/memory.py
procclean/core/models.py
procclean/core/process.py
procclean/formatters/__init__.py
procclean/formatters/columns.py
procclean/formatters/output.py
procclean/tui/__init__.py
procclean/tui/app.py
procclean/tui/app.tcss
procclean/tui/screens.py
procclean-2.0.0.dist-info/licenses/LICENSE
procclean-2.0.0.dist-info/WHEEL
procclean-2.0.0.dist-info/entry_points.txt
procclean-2.0.0.dist-info/METADATA
procclean-2.0.0.dist-info/RECORD
