Metadata-Version: 2.4
Name: procclean
Version: 2.0.0
Summary: Interactive TUI for exploring and cleaning up processes - find orphans, memory hogs, and kill them
Keywords: cleanup,kill,memory,orphan,process,terminal,tui
Author: Kaj Kowalski
Author-email: Kaj Kowalski <info@kajkowalski.nl>
License-Expression: MIT
License-File: LICENSE
Classifier: Development Status :: 5 - Production/Stable
Classifier: Environment :: Console
Classifier: Intended Audience :: Developers
Classifier: Intended Audience :: System Administrators
Classifier: License :: OSI Approved :: MIT License
Classifier: Operating System :: POSIX :: Linux
Classifier: Programming Language :: Python :: 3
Classifier: Programming Language :: Python :: 3.14
Classifier: Topic :: System :: Monitoring
Classifier: Topic :: System :: Systems Administration
Classifier: Topic :: Utilities
Requires-Dist: psutil>=7.2.1
Requires-Dist: tabulate>=0.9.0
Requires-Dist: textual>=7.0.0
Requires-Python: >=3.14
Project-URL: Homepage, https://procclean.kjanat.com
Project-URL: Issues, https://github.com/kjanat/procclean/issues
Project-URL: Repository, https://github.com/kjanat/procclean
